edsudoku/board.py
edsudoku/exceptions.py
edsudoku/generator.py
edsudoku/runserver.py
edsudoku/wsgi.py
edsudoku/__init__.py
edsudoku/impl/board.py
edsudoku/impl/cell.py
edsudoku/impl/group.py
edsudoku/impl/__init__.py
edsudoku/server/boards.py
edsudoku/server/converters.py
edsudoku/server/database.py
edsudoku/server/default_config.py
edsudoku/server/init_db.py
edsudoku/server/login.py
edsudoku/server/manage_users.py
edsudoku/server/misc.py
edsudoku/server/my_boards.py
edsudoku/server/other_users_boards.py
edsudoku/server/pdf.py
edsudoku/server/upgrade_db.py
edsudoku/server/users.py
edsudoku/server/view_boards.py
edsudoku/server/__init__.py
edsudoku/server/fonts/glyphicons-halflings-regular.eot
edsudoku/server/fonts/glyphicons-halflings-regular.svg
edsudoku/server/fonts/glyphicons-halflings-regular.ttf
edsudoku/server/fonts/glyphicons-halflings-regular.woff
edsudoku/server/fonts/glyphicons-halflings-regular.woff2
edsudoku/server/static/board.css
edsudoku/server/static/bootstrap-theme.min.css
edsudoku/server/static/bootstrap.min.css
edsudoku/server/static/bootstrap.min.js
edsudoku/server/static/customization.css
edsudoku/server/static/jquery-2.1.4.min.js
edsudoku/server/templates/create_board.html
edsudoku/server/templates/delete_user.html
edsudoku/server/templates/edit_user.html
edsudoku/server/templates/html_board.html
edsudoku/server/templates/layout.html
edsudoku/server/templates/list_boards.html
edsudoku/server/templates/list_users.html
edsudoku/server/templates/login.html
edsudoku/server/templates/main_page.html
edsudoku/server/templates/pdf_board.tex
edsudoku/server/templates/print_board.html
edsudoku/server/templates/register.html
edsudoku/server/templates/view_board.html
edsudoku-2.0.2.dist-info/DESCRIPTION.rst
edsudoku-2.0.2.dist-info/entry_points.txt
edsudoku-2.0.2.dist-info/METADATA
edsudoku-2.0.2.dist-info/metadata.json
edsudoku-2.0.2.dist-info/RECORD
edsudoku-2.0.2.dist-info/top_level.txt
edsudoku-2.0.2.dist-info/WHEEL
