Metadata-Version: 2.0
Name: edsudoku
Version: 2.0.2
Summary: Utility and website for generating solvable sudoku puzzles
Home-page: https://github.com/elidaian/edsudoku
Author: Eli Daian
Author-email: elidaian@gmail.com
License: GPL
Keywords: sudoku server
Platform: UNKNOWN
Classifier: Development Status :: 2 - Pre-Alpha
Classifier: Environment :: Console
Classifier: Environment :: Web Environment
Classifier: Framework :: Flask
Classifier: Intended Audience :: Developers
Classifier: Intended Audience :: End Users/Desktop
Classifier: License :: OSI Approved :: GNU General Public License v3 (GPLv3)
Classifier: Natural Language :: English
Classifier: Operating System :: OS Independent
Classifier: Programming Language :: Python :: 2.7
Classifier: Topic :: Games/Entertainment :: Board Games
Classifier: Topic :: Games/Entertainment :: Puzzle Games
Classifier: Topic :: Internet :: WWW/HTTP :: WSGI :: Application
Requires-Dist: flask
Requires-Dist: sqlalchemy
